Workbook
Name FromArray_1: _xlfn.ANCHORARRAY(Dashboard!$B$10)

Sheet Dashboard
AM1: Inventory | AN1: =SUMIFS(Revenue!P:P, Revenue!E:E, "Inventory", Revenue!D:D, "Active") -> 46500
B2: 月度总营收 (Active MRR) | C2: 月度总毛利 (Total Monthly Profit) | D2: 综合毛利率 (Avg. Margin %) | E2: 总售出容量 (Total Sold Capacity) | G2: 销售排行 | AM2: Resale | AN2: =SUMIFS(Revenue!P:P, Revenue!E:E, "Resale", Revenue!D:D, "Active") -> 53500
B3: =SUMIFS(Revenue!P:P, Revenue!D:D, "Active") -> 104020.83 | C3: =SUMIFS(Revenue!AW:AW, Revenue!D:D, "Active") -> 90868.056 | D3: =C3/B3 -> 0.87355631 | E3: =SUMIFS(Revenue!AT:AT, Revenue!D:D, "Active") & " Gbps" -> 330 Gbps | G3: 销售经理 | H3: 贡献毛利 | AM3: Hybrid | AN3: =SUMIFS(Revenue!P:P, Revenue!E:E, "Hybrid", Revenue!D:D, "Active") -> 4020.8333
G4: {=_xlfn.LET(_xlpm.NameList, Revenue!C:C, _xlpm.StatusList, Revenue!D:D, _xlpm.TypeList, Revenue!E:E, _xlpm.MarginList, Revenue!AW:AW, _xlpm.ValidRows, (_xlpm.NameList<>"")*(_xlpm.StatusList="Active")*(_xlpm.TypeList<>"置换出")*(_xlpm.NameList<>"Procument Dept"), _xlpm.UniqueNames, _xlfn.UNIQUE(_xlfn._xlws.FILTER(_xlpm.NameList, _xlpm.ValidRows, "暂无数据")), IF(INDEX(_xlpm.UniqueNames,1,1)="暂无数据", "暂无数据", _xlfn.SORTBY(_xlpm.UniqueNames, SUMIFS(_xlpm.MarginList, _xlpm.NameList, _xlpm.UniqueNames, _xlpm.StatusList, "Active", _xlpm.TypeList, "<>置换出"), -1)))} -> Janna | H4: {=IF(OR(G4="", G4="暂无数据"), "", SUMIFS(Revenue!AW:AW, Revenue!C:C,_xlfn.ANCHORARRAY( G4), Revenue!D:D, "Active", Revenue!E:E, "<>置换出", Revenue!E:E, "<>Swapped out"))} -> 67988.889
G5: Wayne | H5: 25450
G6: Miki | H6: 2016.6667
B8: 销售续约清单 (<3个月)
B9: 客户 | C9: 销售经理 | D9: 到期日 | E9: 剩余天数
B10: {=_xlfn._xlws.FILTER(CHOOSE({1,2,3,4}, Revenue!B:B, Revenue!C:C, Revenue!K:K, Revenue!K:K-TODAY()), (Revenue!AZ:AZ="🔥 Renew Now (<3m)")*(Revenue!D:D="Active"), "无紧急续约")} -> ByteDance | C10: Wayne | D10: 46053 | E10: 26
B11: China Unicom (Hong Kong) Operations Limited | C11: Janna | D11: 46036 | E11: 9
B18: Inventory 资源续约清单
B19: Resource ID | C19: Supplier | D19: End Date | E19: Days Left
B20: {=_xlfn._xlws.FILTER(CHOOSE({1,2,3,4}, Inventory!A:A, Inventory!L:L, Inventory!P:P, Inventory!P:P-TODAY()), (Inventory!AE:AE<>"OK")*(Inventory!AE:AE<>"")*(Inventory!AE:AE<>"Expiry Alert"), "✅ 上游资源健康")} -> INV-ADC-001 | C20: NTT | D20: 46081 | E20: 54

Sheet Inventory
A1: Resource ID | B1: Acquisition Type | C1: Contract/Agreement Ref | D1: Ownership | E1: Cable System | F1: Segement Type | G1: Route Descr. | H1: Capacity Size (Gbps) | I1: Unit | J1: Protection | K1: Protection Sys | L1: Supplier | M1: Procument Model | N1: Term (Months) | O1: Start Date | P1: End Date | Q1: OTC (NRC / CapEx) | R1: O&M Rate | S1: Annual OpEx | T1: Monthly Lease | U1: A-END Country | V1: A-END City | W1: A-END PoP Site | X1: A-END Port | Y1: Z-END Country | Z1: Z-END City | AA1: Z-END PoP Site | AB1: Z-END Port | AC1: Used Capacity | AD1: Remaining | AE1: Expiry Alert | AF1: Status | AG1: Current User | AH1: Order Link
A2: INV-JUNO-001 | B2: Purchased | C2: CTR-2024-001 | D2: 本公司 | E2: Juno | F2: Capacity | G2: Tokyo - Los Angeles | H2: 100 | I2: Gbps | J2: Unprotected | K2: N/A | L2: PCCW | M2: IRU | N2: 180 | O2: 45658 | P2: =EDATE(O2, N2)-1 -> 51135 | Q2: 450000 | R2: 0.045 | S2: =Q2 * R2 -> 20250 | T2: 0 | U2: JP | V2: Tokyo | W2: Shin-Maruyama CLS | X2: Port-J1 | Y2: US | Z2: Los Angeles | AA2: CoreSite LA2 | AB2: Port-LA1 | AC2: =SUMIFS(Revenue!AT:AT, Revenue!F:F, A2, Revenue!D:D, "Active") -> 20 | AD2: =H2 - AC2 -> 80 | AE2: =IF(P2="", "", IF(P2 < TODAY(), "Expired", IF(P2 - TODAY() < 180, "⚠️ Renew Soon (<6m)", "OK"))) -> OK | AF2: =IF(OR(O2="", P2=""), "Draft", IF(TODAY() > P2, "Expired", IF(AD2 <= 0, "Sold Out", "Available"))) -> Available | AG2: {=_xlfn.TEXTJOIN(", ", TRUE, _xlfn._xlws.FILTER(Revenue!B:B, (Revenue!F:F=A2)*(Revenue!D:D="Active"), ""))} -> Meta | AH2: {=_xlfn.TEXTJOIN(", ", TRUE, _xlfn._xlws.FILTER(Revenue!A:A, (Revenue!F:F=A2)*(Revenue!D:D="Active"), ""))} -> SO-2025-003
A3: INV-JUNO-002 | B3: Purchased | C3: CTR-2024-001 | D3: 本公司 | E3: Juno | F3: Capacity | G3: Tokyo - Los Angeles | H3: 100 | I3: Gbps | J3: Protected | K3: ADC | L3: PCCW | M3: IRU | N3: 180 | O3: 45658 | P3: =EDATE(O3, N3)-1 -> 51135 | Q3: 450000 | R3: 0.045 | S3: =Q3 * R3 -> 20250 | T3: 0 | U3: JP | V3: Tokyo | W3: Shin-Maruyama CLS | X3: Port-J2 | Y3: US | Z3: Los Angeles | AA3: CoreSite LA2 | AB3: Port-LA2 | AC3: =SUMIFS(Revenue!AT:AT, Revenue!F:F, A3, Revenue!D:D, "Active") -> 100 | AD3: =H3 - AC3 -> 0 | AE3: =IF(P3="", "", IF(P3 < TODAY(), "Expired", IF(P3 - TODAY() < 180, "⚠️ Renew Soon (<6m)", "OK"))) -> OK | AF3: =IF(OR(O3="", P3=""), "Draft", IF(TODAY() > P3, "Expired", IF(AD3 <= 0, "Sold Out", "Available"))) -> Sold Out | AG3: {=_xlfn.TEXTJOIN(", ", TRUE, _xlfn._xlws.FILTER(Revenue!B:B, (Revenue!F:F=A3)*(Revenue!D:D="Active"), ""))} -> Google | AH3: {=_xlfn.TEXTJOIN(", ", TRUE, _xlfn._xlws.FILTER(Revenue!A:A, (Revenue!F:F=A3)*(Revenue!D:D="Active"), ""))} -> SO-SWAP-001
A4: INV-SJC2-001 | B4: Swapped In | C4: SWAP-2024-88 | D4: Google | E4: SJC2 | F4: Capacity | G4: Singapore - Hong Kong | H4: 100 | I4: Gbps | J4: Protected | K4: Self-Protected Ring | L4: Singtel | M4: IRU | N4: 180 | O4: 45809 | P4: =EDATE(O4, N4)-1 -> 51287 | Q4: 0 | R4: 0 | S4: =Q4 * R4 -> 0 | T4: 0 | U4: SG | V4: Singapore | W4: Equinix SG1 | X4: Port-S1 | Y4: HK | Z4: Hong Kong | AA4: Mega-i | AB4: Port-H1 | AC4: =SUMIFS(Revenue!AT:AT, Revenue!F:F, A4, Revenue!D:D, "Active") -> 0 | AD4: =H4 - AC4 -> 100 | AE4: =IF(P4="", "", IF(P4 < TODAY(), "Expired", IF(P4 - TODAY() < 180, "⚠️ Renew Soon (<6m)", "OK"))) -> OK | AF4: =IF(OR(O4="", P4=""), "Draft", IF(TODAY() > P4, "Expired", IF(AD4 <= 0, "Sold Out", "Available"))) -> Available | AG4: {=_xlfn.TEXTJOIN(", ", TRUE, _xlfn._xlws.FILTER(Revenue!B:B, (Revenue!F:F=A4)*(Revenue!D:D="Active"), ""))} | AH4: {=_xlfn.TEXTJOIN(", ", TRUE, _xlfn._xlws.FILTER(Revenue!A:A, (Revenue!F:F=A4)*(Revenue!D:D="Active"), ""))}
A5: INV-ADC-001 | B5: Purchased | C5: LSE-2025-002 | D5: NTT | E5: ADC | F5: Capacity | G5: Singapore - Tokyo | H5: 100 | I5: Gbps | J5: Unprotected | K5: N/A | L5: NTT | M5: Lease | N5: 12 | O5: 45717 | P5: =EDATE(O5, N5)-1 -> 46081 | Q5: 2000 | R5: 0 | S5: =Q5 * R5 -> 0 | T5: 3500 | U5: SG | V5: Singapore | W5: Equinix SG1 | X5: Port-S2 | Y5: JP | Z5: Tokyo | AA5: Shin-Maruyama CLS | AB5: Port-J3 | AC5: =SUMIFS(Revenue!AT:AT, Revenue!F:F, A5, Revenue!D:D, "Active") -> 10 | AD5: =H5 - AC5 -> 90 | AE5: =IF(P5="", "", IF(P5 < TODAY(), "Expired", IF(P5 - TODAY() < 180, "⚠️ Renew Soon (<6m)", "OK"))) -> ⚠️ Renew Soon (<6m) | AF5: =IF(OR(O5="", P5=""), "Draft", IF(TODAY() > P5, "Expired", IF(AD5 <= 0, "Sold Out", "Available"))) -> Available | AG5: {=_xlfn.TEXTJOIN(", ", TRUE, _xlfn._xlws.FILTER(Revenue!B:B, (Revenue!F:F=A5)*(Revenue!D:D="Active"), ""))} -> Google | AH5: {=_xlfn.TEXTJOIN(", ", TRUE, _xlfn._xlws.FILTER(Revenue!A:A, (Revenue!F:F=A5)*(Revenue!D:D="Active"), ""))} -> SO-2025-002
A6: INV-APRICOT-01 | B6: Purchased | C6: CTR-2025-99 | D6: 本公司 | E6: Apricot | F6: Fiber Pair | G6: Tokyo - Singapore | H6: 12000 | I6: Half Fiber Pair | J6: Unprotected | K6: N/A | L6: Google | M6: IRU | N6: 240 | O6: 46023 | P6: =EDATE(O6, N6)-1 -> 53327 | Q6: 2000000 | R6: 0.03 | S6: =Q6 * R6 -> 60000 | T6: 0 | U6: JP | V6: Tokyo | W6: Shin-Maruyama CLS | X6: Port-TBD | Y6: SG | Z6: Singapore | AA6: Equinix SG3 | AB6: Port-TBD | AC6: =SUMIFS(Revenue!AT:AT, Revenue!F:F, A6, Revenue!D:D, "Active") -> 100 | AD6: =H6 - AC6 -> 11900 | AE6: =IF(P6="", "", IF(P6 < TODAY(), "Expired", IF(P6 - TODAY() < 180, "⚠️ Renew Soon (<6m)", "OK"))) -> OK | AF6: =IF(OR(O6="", P6=""), "Draft", IF(TODAY() > P6, "Expired", IF(AD6 <= 0, "Sold Out", "Available"))) -> Available | AG6: {=_xlfn.TEXTJOIN(", ", TRUE, _xlfn._xlws.FILTER(Revenue!B:B, (Revenue!F:F=A6)*(Revenue!D:D="Active"), ""))} -> Microsoft | AH6: {=_xlfn.TEXTJOIN(", ", TRUE, _xlfn._xlws.FILTER(Revenue!A:A, (Revenue!F:F=A6)*(Revenue!D:D="Active"), ""))} -> SO-2026-001

Sheet Revenue
A1: Sales Order ID | B1: Customer Name | C1: Account Manager | D1: Sales Status | E1: Sales Type | F1: Inventory Link | G1: Cust. A-End Site | H1: Cust. Z-End Site | I1: Term (Months) | J1: Start Date | K1: End Date | L1: NRC Sales | M1: MRC Sales | N1: Sales O&M Rate | O1: Annual Sales | P1: Total MRR | Q1: Cable Supplier | R1: 3rd Party System | S1: Ref: Cost PO (Cable) | T1: Cost Model | U1: Amort. Months | V1: Annual O&M (Cable) | W1: Cable NRC Cost | X1: Cable Cost Amount | Y1: BH Supplier (A-End) | Z1: Ref: Cost PO (BH-A) | AA1: BH NRC (A) | AB1: BH Cost (A-End) | AC1: BH Supplier (Z-End) | AD1: Ref: Cost PO (BH-Z) | AE1: BH NRC (Z) | AF1: BH Cost (Z-End) | AG1: XC Supplier (A-End) | AH1: Ref: Cost PO (XC-A) | AI1: XC NRC (A) | AJ1: XC Cost (A-End) | AK1: XC Supplier (Z-End) | AL1: Ref: Cost PO (XC-Z) | AM1: XC NRC (Z) | AN1: XC Cost (Z-End) | AO1: SH Supplier | AP1: Ref: Cost PO (SH) | AQ1: Smart Hands (One-off) | AR1: Total Direct MRC | AS1: Total Direct NRC | AT1: Sales Capacity | AU1: Allocated Monthly Cost | AV1: Total Monthly Cost | AW1: Gross Margin ($) | AX1: Margin (%) | AY1: NRC Profit | AZ1: Renewal Alert
A2: SO-2026-001 | B2: Microsoft | C2: Janna | D2: =IF(OR(J2="", K2=""), "", IF(TODAY() > K2, "Expired", IF(TODAY() < J2, "Pending", "Active"))) -> Active | E2: Inventory | F2: INV-APRICOT-01 | G2: Tokyo CoreSite | H2: Singapore SG3 | I2: 36 | J2: 45658 | K2: =EDATE(J2, I2)-1 -> 46752 | L2: 5000 | M2: 45000 | N2: 0 | O2: =L2 * N2 -> 0 | P2: =M2 + O2/12 -> 45000 | T2: IRU | X2: 0 | AB2: 0 | AF2: 0 | AG2: Equinix | AH2: PO-XC-101 | AJ2: 200 | AK2: CoreSite | AL2: PO-XC-102 | AN2: 200 | AQ2: 0 | AR2: =IF(T2="IRU", (X2/IF(U2="",1,U2)) + V2/12, X2) + AB2 + AF2 + AJ2 + AN2 -> 400 | AS2: =SUM(W2, AA2, AE2, AI2, AM2, AQ2) -> 0 | AT2: 100 | AU2: {=IF(F2="", 0, IFERROR(_xlfn.XLOOKUP(F2, Inventory!A:A, (Inventory!S:S/12 + Inventory!T:T + Inventory!Q:Q/Inventory!N:N) / Inventory!H:H) * AT2, 0))} -> 111.11111 | AV2: =AR2 + AU2 -> 511.11111 | AW2: =P2 - AV2 -> 44488.889 | AX2: =IF(P2=0, 0, AW2/P2) -> 0.98864198 | AY2: =L2 - AS2 -> 5000 | AZ2: =IF(OR(D2<>"Active", K2=""), "", IF(K2 < TODAY(), "Expired", IF(K2 - TODAY() < 90, "🔥 Renew Now (<3m)", IF(K2 - TODAY() < 180, "⚠️ Plan Renewal (<6m)", "OK")))) -> OK
A3: SO-2026-002 | B3: HFT Capital | C3: Janna | D3: =IF(OR(J3="", K3=""), "", IF(TODAY() > K3, "Expired", IF(TODAY() < J3, "Pending", "Active"))) -> Pending | E3: Inventory | F3: INV-APRICOT-01 | G3: Tokyo CoreSite | H3: Singapore SG3 | I3: 12 | J3: 46204 | K3: =EDATE(J3, I3)-1 -> 46568 | L3: 2000 | M3: 1500 | N3: 0 | O3: =L3 * N3 -> 0 | P3: =M3 + O3/12 -> 1500 | T3: IRU | X3: 0 | AB3: 0 | AF3: 0 | AG3: Equinix | AH3: PO-XC-103 | AJ3: 200 | AK3: CoreSite | AL3: PO-XC-104 | AN3: 200 | AQ3: 0 | AR3: =IF(T3="IRU", (X3/IF(U3="",1,U3)) + V3/12, X3) + AB3 + AF3 + AJ3 + AN3 -> 400 | AS3: =SUM(W3, AA3, AE3, AI3, AM3, AQ3) -> 0 | AT3: 10 | AU3: {=IF(F3="", 0, IFERROR(_xlfn.XLOOKUP(F3, Inventory!A:A, (Inventory!S:S/12 + Inventory!T:T + Inventory!Q:Q/Inventory!N:N) / Inventory!H:H) * AT3, 0))} -> 11.111111 | AV3: =AR3 + AU3 -> 411.11111 | AW3: =P3 - AV3 -> 1088.8889 | AX3: =IF(P3=0, 0, AW3/P3) -> 0.72592593 | AY3: =L3 - AS3 -> 2000 | AZ3: =IF(OR(D3<>"Active", K3=""), "", IF(K3 < TODAY(), "Expired", IF(K3 - TODAY() < 90, "🔥 Renew Now (<3m)", IF(K3 - TODAY() < 180, "⚠️ Plan Renewal (<6m)", "OK"))))
A4: SO-2025-002 | B4: Google | C4: Miki | D4: =IF(OR(J4="", K4=""), "", IF(TODAY() > K4, "Expired", IF(TODAY() < J4, "Pending", "Active"))) -> Active | E4: Inventory | F4: INV-ADC-001 | G4: Singapore SG1 | H4: Tokyo SM-CLS | I4: 24 | J4: 45748 | K4: =EDATE(J4, I4)-1 -> 46477 | L4: 1000 | M4: 1500 | N4: 0 | O4: =L4 * N4 -> 0 | P4: =M4 + O4/12 -> 1500 | T4: IRU | X4: 0 | AB4: 0 | AF4: 0 | AG4: Equinix | AH4: PO-XC-201 | AJ4: 200 | AK4: NTT | AL4: PO-XC-202 | AN4: 200 | AQ4: 0 | AR4: =IF(T4="IRU", (X4/IF(U4="",1,U4)) + V4/12, X4) + AB4 + AF4 + AJ4 + AN4 -> 400 | AS4: =SUM(W4, AA4, AE4, AI4, AM4, AQ4) -> 0 | AT4: 10 | AU4: {=IF(F4="", 0, IFERROR(_xlfn.XLOOKUP(F4, Inventory!A:A, (Inventory!S:S/12 + Inventory!T:T + Inventory!Q:Q/Inventory!N:N) / Inventory!H:H) * AT4, 0))} -> 366.66667 | AV4: =AR4 + AU4 -> 766.66667 | AW4: =P4 - AV4 -> 733.33333 | AX4: =IF(P4=0, 0, AW4/P4) -> 0.48888889 | AY4: =L4 - AS4 -> 1000 | AZ4: =IF(OR(D4<>"Active", K4=""), "", IF(K4 < TODAY(), "Expired", IF(K4 - TODAY() < 90, "🔥 Renew Now (<3m)", IF(K4 - TODAY() < 180, "⚠️ Plan Renewal (<6m)", "OK")))) -> OK
A5: SO-2025-003 | B5: Meta | C5: Miki | D5: =IF(OR(J5="", K5=""), "", IF(TODAY() > K5, "Expired", IF(TODAY() < J5, "Pending", "Active"))) -> Active | E5: Hybrid | F5: INV-JUNO-001 | G5: Tokyo SM-CLS | H5: Las Vegas Switch | I5: 36 | J5: 45658 | K5: =EDATE(J5, I5)-1 -> 46752 | L5: 5000 | M5: 4000 | N5: 0.05 | O5: =L5 * N5 -> 250 | P5: =M5 + O5/12 -> 4020.8333 | Q5: Zayo | R5: PC-1 | S5: PO-CBL-301 | T5: IRU | X5: 1500 | AB5: 0 | AF5: 0 | AG5: NTT | AH5: PO-XC-301 | AJ5: 200 | AK5: Switch | AL5: PO-XC-302 | AN5: 200 | AQ5: 0 | AR5: =IF(T5="IRU", (X5/IF(U5="",1,U5)) + V5/12, X5) + AB5 + AF5 + AJ5 + AN5 -> 1900 | AS5: =SUM(W5, AA5, AE5, AI5, AM5, AQ5) -> 0 | AT5: 20 | AU5: {=IF(F5="", 0, IFERROR(_xlfn.XLOOKUP(F5, Inventory!A:A, (Inventory!S:S/12 + Inventory!T:T + Inventory!Q:Q/Inventory!N:N) / Inventory!H:H) * AT5, 0))} -> 837.5 | AV5: =AR5 + AU5 -> 2737.5 | AW5: =P5 - AV5 -> 1283.3333 | AX5: =IF(P5=0, 0, AW5/P5) -> 0.31917098 | AY5: =L5 - AS5 -> 5000 | AZ5: =IF(OR(D5<>"Active", K5=""), "", IF(K5 < TODAY(), "Expired", IF(K5 - TODAY() < 90, "🔥 Renew Now (<3m)", IF(K5 - TODAY() < 180, "⚠️ Plan Renewal (<6m)", "OK")))) -> OK
A6: SO-2025-001 | B6: ByteDance | C6: Wayne | D6: =IF(OR(J6="", K6=""), "", IF(TODAY() > K6, "Expired", IF(TODAY() < J6, "Pending", "Active"))) -> Active | E6: Resale | G6: Equinix SG1 | H6: Mega-i HK | I6: 12 | J6: 45689 | K6: =EDATE(J6, I6)-1 -> 46053 | L6: 2000 | M6: 30000 | N6: 0 | O6: =L6 * N6 -> 0 | P6: =M6 + O6/12 -> 30000 | Q6: PCCW | R6: AAG | S6: PO-CBL-001 | T6: IRU | X6: 3000 | Y6: Singtel | Z6: PO-BH-001 | AB6: 500 | AC6: HKBN | AD6: PO-BH-002 | AF6: 600 | AG6: Equinix | AH6: PO-XC-001 | AJ6: 200 | AK6: Mega-i | AL6: PO-XC-002 | AN6: 250 | AO6: Gbic($300)+Eqx($200) | AP6: PO-SH-001 | AQ6: 500 | AR6: =IF(T6="IRU", (X6/IF(U6="",1,U6)) + V6/12, X6) + AB6 + AF6 + AJ6 + AN6 -> 4550 | AS6: =SUM(W6, AA6, AE6, AI6, AM6, AQ6) -> 500 | AT6: 100 | AU6: {=IF(F6="", 0, IFERROR(_xlfn.XLOOKUP(F6, Inventory!A:A, (Inventory!S:S/12 + Inventory!T:T + Inventory!Q:Q/Inventory!N:N) / Inventory!H:H) * AT6, 0))} -> 0 | AV6: =AR6 + AU6 -> 4550 | AW6: =P6 - AV6 -> 25450 | AX6: =IF(P6=0, 0, AW6/P6) -> 0.84833333 | AY6: =L6 - AS6 -> 1500 | AZ6: =IF(OR(D6<>"Active", K6=""), "", IF(K6 < TODAY(), "Expired", IF(K6 - TODAY() < 90, "🔥 Renew Now (<3m)", IF(K6 - TODAY() < 180, "⚠️ Plan Renewal (<6m)", "OK")))) -> 🔥 Renew Now (<3m)
A7: SO-SWAP-001 | B7: Google | C7: Procument Dept | D7: =IF(OR(J7="", K7=""), "", IF(TODAY() > K7, "Expired", IF(TODAY() < J7, "Pending", "Active"))) -> Active | E7: Swapped out | F7: INV-JUNO-002 | G7: Tokyo | H7: LA | I7: 180 | J7: 45809 | K7: =EDATE(J7, I7)-1 -> 51287 | L7: 0 | M7: 0 | N7: 0 | O7: =L7 * N7 -> 0 | P7: =M7 + O7/12 -> 0 | T7: IRU | X7: 0 | AB7: 0 | AF7: 0 | AG7: NTT | AH7: PO-XC-SW01 | AJ7: 200 | AK7: CoreSite | AL7: PO-XC-SW02 | AN7: 200 | AQ7: 0 | AR7: =IF(T7="IRU", (X7/IF(U7="",1,U7)) + V7/12, X7) + AB7 + AF7 + AJ7 + AN7 -> 400 | AS7: =SUM(W7, AA7, AE7, AI7, AM7, AQ7) -> 0 | AT7: 100 | AU7: {=IF(F7="", 0, IFERROR(_xlfn.XLOOKUP(F7, Inventory!A:A, (Inventory!S:S/12 + Inventory!T:T + Inventory!Q:Q/Inventory!N:N) / Inventory!H:H) * AT7, 0))} -> 4187.5 | AV7: =AR7 + AU7 -> 4587.5 | AW7: =P7 - AV7 -> -4587.5 | AX7: =IF(P7=0, 0, AW7/P7) -> 0 | AY7: =L7 - AS7 -> 0 | AZ7: =IF(OR(D7<>"Active", K7=""), "", IF(K7 < TODAY(), "Expired", IF(K7 - TODAY() < 90, "🔥 Renew Now (<3m)", IF(K7 - TODAY() < 180, "⚠️ Plan Renewal (<6m)", "OK")))) -> OK
A8: OB-202401000045 | B8: China Unicom (Hong Kong) Operations Limited | C8: Janna | D8: =IF(OR(J8="", K8=""), "", IF(TODAY() > K8, "Expired", IF(TODAY() < J8, "Pending", "Active"))) -> Active | E8: Resale | G8: Equinix HK1 | H8: Coresite LA2 | I8: 24 | J8: 45306 | K8: =EDATE(J8, I8)-1 -> 46036 | L8: 1600 | M8: 23500 | N8: 0 | O8: =L8 * N8 -> 0 | P8: =M8 + O8/12 -> 23500 | Q8: TELEKOM MALAYSIA(HONGKONG) LIMITED | R8: ASE & JUPITER | S8: IE1095336065 | T8: Lease | U8: 1 | V8: 0 | W8: 12000 | X8: 22500 | AB8: 0 | AU8: {=IF(F8="", 0, IFERROR(_xlfn.XLOOKUP(F8, Inventory!A:A, (Inventory!S:S/12 + Inventory!T:T + Inventory!Q:Q/Inventory!N:N) / Inventory!H:H) * AT8, 0))} -> 0 | AV8: =AR8 + AU8 -> 0 | AW8: =P8 - AV8 -> 23500 | AX8: =IF(P8=0, 0, AW8/P8) -> 1 | AY8: =L8 - AS8 -> 1600 | AZ8: =IF(OR(D8<>"Active", K8=""), "", IF(K8 < TODAY(), "Expired", IF(K8 - TODAY() < 90, "🔥 Renew Now (<3m)", IF(K8 - TODAY() < 180, "⚠️ Plan Renewal (<6m)", "OK")))) -> 🔥 Renew Now (<3m)
